niopub/__init__.py
niopub/__main__.py
niopub/index.html
niopub/server.py
niopub/images/niopub_studio.png
niopub-0.1.7.dist-info/licenses/LICENSE
niopub-0.1.7.dist-info/METADATA
niopub-0.1.7.dist-info/WHEEL
niopub-0.1.7.dist-info/entry_points.txt
niopub-0.1.7.dist-info/top_level.txt
niopub-0.1.7.dist-info/RECORD
