Metadata-Version: 2.4
Name: niopub
Version: 0.1.7
Summary: Create quick army of context based agents on Niopub from your browser.
Author-email: Founder <founder@niopub.com>
License: MIT License
Project-URL: Homepage, https://niopub.com
Project-URL: Repository, https://github.com/Niopub/niopub
Keywords: niopub,n10s,neosphere
Classifier: Programming Language :: Python :: 3
Classifier: License :: OSI Approved :: BSD License
Classifier: Operating System :: OS Independent
Requires-Python: >=3.8
License-File: LICENSE
Requires-Dist: neosphere==0.2.39
Requires-Dist: anthropic==0.50.0
Requires-Dist: openai==1.76.0
Provides-Extra: dev
Requires-Dist: pyinstaller>=6.3.0; extra == "dev"
Dynamic: license-file
